{"AXON": {"2021-02-16": {"300 Day(s) Before": null, "100 Day(s) Before": null, "30 Day(s) Before": null, "10 Day(s) Before": null, "3 Day(s) Before": null, "1 Day(s) Before": null, "1 Day(s) After": -0.9199999999999875, "3 Day(s) After": 0.07001000000002477, "8 Day(s) After": -15.919999999999987, "13 Day(s) After": -47.91001, "21 Day(s) After": -33.41999999999999, "34 Day(s) After": -30.859999999999985, "100 Day(s) After": null, "200 Day(s) After": null, "300 Day(s) After": null, "400 Day(s) After": null}, "2021-02-17": {"300 Day(s) Before": null, "100 Day(s) Before": null, "30 Day(s) Before": null, "10 Day(s) Before": null, "3 Day(s) Before": null, "1 Day(s) Before": -0.9199999999999875, "1 Day(s) After": -3.8700000000000045, "3 Day(s) After": -6.050000000000011, "8 Day(s) After": -7.780000000000001, "13 Day(s) After": -37.5, "21 Day(s) After": -36.110000000000014, "34 Day(s) After": -30.53998999999999, "100 Day(s) After": null, "200 Day(s) After": null, "300 Day(s) After": null, "400 Day(s) After": null}, "2021-02-18": {"300 Day(s) Before": null, "100 Day(s) Before": null, "30 Day(s) Before": null, "10 Day(s) Before": null, "3 Day(s) Before": null, "1 Day(s) Before": -3.8700000000000045, "1 Day(s) After": 4.860010000000017, "3 Day(s) After": -14.240000000000009, "8 Day(s) After": -7.639989999999983, "13 Day(s) After": -28.05999, "21 Day(s) After": -33.25999999999999, "34 Day(s) After": -23.620010000000008, "100 Day(s) After": null, "200 Day(s) After": null, "300 Day(s) After": null, "400 Day(s) After": null}, "2021-02-19": {"300 Day(s) Before": null, "100 Day(s) Before": null, "30 Day(s) Before": null, "10 Day(s) Before": null, "3 Day(s) Before": 0.07001000000002477, "1 Day(s) Before": 4.860010000000017, "1 Day(s) After": -7.040010000000024, "3 Day(s) After": -15.960010000000011, "8 Day(s) After": -22.050010000000015, "13 Day(s) After": -35.56002000000001, "21 Day(s) After": -31.66001, "34 Day(s) After": -30.640000000000015, "100 Day(s) After": null, "200 Day(s) After": null, "300 Day(s) After": null, "400 Day(s) After": null}, "2021-02-22": {"300 Day(s) Before": null, "100 Day(s) Before": null, "30 Day(s) Before": null, "10 Day(s) Before": null, "3 Day(s) Before": -6.050000000000011, "1 Day(s) Before": -7.040010000000024, "1 Day(s) After": -12.060000000000002, "3 Day(s) After": -10.449999999999989, "8 Day(s) After": -30.69001, "13 Day(s) After": -22.829999999999984, "21 Day(s) After": -30.149999999999977, "34 Day(s) After": -23.44999999999999, "100 Day(s) After": null, "200 Day(s) After": null, "300 Day(s) After": null, "400 Day(s) After": null}, "2021-02-23": {"300 Day(s) Before": null, "100 Day(s) Before": null, "30 Day(s) Before": null, "10 Day(s) Before": null, "3 Day(s) Before": -14.240000000000009, "1 Day(s) Before": -12.060000000000002, "1 Day(s) After": 3.140000000000015, "3 Day(s) After": 3.1100000000000136, "8 Day(s) After": -28.88001, "13 Day(s) After": -9.529999999999973, "21 Day(s) After": -23.839999999999975, "34 Day(s) After": -8.130009999999999, "100 Day(s) After": null, "200 Day(s) After": null, "300 Day(s) After": null, "400 Day(s) After": null}, "2021-02-24": {"300 Day(s) Before": null, "100 Day(s) Before": null, "30 Day(s) Before": null, "10 Day(s) Before": null, "3 Day(s) Before": -15.960010000000011, "1 Day(s) Before": 3.140000000000015, "1 Day(s) After": -1.5300000000000011, "3 Day(s) After": 7.189999999999998, "8 Day(s) After": -22.53, "13 Day(s) After": -9.400000000000006, "21 Day(s) After": -32.78, "34 Day(s) After": -7.939999999999998, "100 Day(s) After": null, "200 Day(s) After": null, "300 Day(s) After": null, "400 Day(s) After": null}, "2021-02-25": {"300 Day(s) Before": null, "100 Day(s) Before": null, "30 Day(s) Before": null, "10 Day(s) Before": null, "3 Day(s) Before": -10.449999999999989, "1 Day(s) Before": -1.5300000000000011, "1 Day(s) After": 1.5, "3 Day(s) After": 4.990010000000012, "8 Day(s) After": -15.429990000000004, "13 Day(s) After": -13.789989999999989, "21 Day(s) After": -26.810000000000002, "34 Day(s) After": -6.5, "100 Day(s) After": null, "200 Day(s) After": null, "300 Day(s) After": null, "400 Day(s) After": null}, "2021-02-26": {"300 Day(s) Before": null, "100 Day(s) Before": null, "30 Day(s) Before": null, "10 Day(s) Before": null, "3 Day(s) Before": 3.1100000000000136, "1 Day(s) Before": 1.5, "1 Day(s) After": 7.219999999999999, "3 Day(s) After": -6.060000000000002, "8 Day(s) After": -19.570009999999996, "13 Day(s) After": -17.5, "21 Day(s) After": -28.179990000000004, "34 Day(s) After": -8.939999999999998, "100 Day(s) After": null, "200 Day(s) After": null, "300 Day(s) After": null, "400 Day(s) After": null}, "2021-03-01": {"300 Day(s) Before": null, "100 Day(s) Before": null, "30 Day(s) Before": null, "10 Day(s) Before": null, "3 Day(s) Before": 7.189999999999998, "1 Day(s) Before": 7.219999999999999, "1 Day(s) After": -3.7299899999999866, "3 Day(s) After": -28.96001000000001, "8 Day(s) After": -21.099999999999994, "13 Day(s) After": -28.330000000000013, "21 Day(s) After": -34.22, "34 Day(s) After": -22.02000000000001, "100 Day(s) After": null, "200 Day(s) After": null, "300 Day(s) After": null, "400 Day(s) After": null}, "2021-03-02": {"300 Day(s) Before": null, "100 Day(s) Before": null, "30 Day(s) Before": null, "10 Day(s) Before": -12.429989999999975, "3 Day(s) Before": 4.990010000000012, "1 Day(s) Before": -3.7299899999999866, "1 Day(s) After": -9.550010000000015, "3 Day(s) After": -35.480020000000025, "8 Day(s) After": -16.13001, "13 Day(s) After": -25.620010000000008, "21 Day(s) After": -23.13001, "34 Day(s) After": -16.230020000000025, "100 Day(s) After": null, "200 Day(s) After": null, "300 Day(s) After": null, "400 Day(s) After": null}, "2021-03-03": {"300 Day(s) Before": null, "100 Day(s) Before": null, "30 Day(s) Before": null, "10 Day(s) Before": -21.060000000000002, "3 Day(s) Before": -6.060000000000002, "1 Day(s) Before": -9.550010000000015, "1 Day(s) After": -15.68001000000001, "3 Day(s) After": -16.439999999999998, "8 Day(s) After": -3.3100000000000023, "13 Day(s) After": -9.609999999999985, "21 Day(s) After": -11.389999999999986, "34 Day(s) After": -6.280000000000001, "100 Day(s) After": null, "200 Day(s) After": null, "300 Day(s) After": null, "400 Day(s) After": null}, "2021-03-04": {"300 Day(s) Before": null, "100 Day(s) Before": null, "30 Day(s) Before": null, "10 Day(s) Before": -32.87001000000001, "3 Day(s) Before": -28.96001000000001, "1 Day(s) Before": -15.68001000000001, "1 Day(s) After": -10.25, "3 Day(s) After": 4.810020000000009, "8 Day(s) After": 6.450020000000023, "13 Day(s) After": 0.5400100000000236, "21 Day(s) After": 5.740010000000012, "34 Day(s) After": 11.84002000000001, "100 Day(s) After": null, "200 Day(s) After": null, "300 Day(s) After": null, "400 Day(s) After": null}, "2021-03-05": {"300 Day(s) Before": null, "100 Day(s) Before": null, "30 Day(s) Before": null, "10 Day(s) Before": -47.980020000000025, "3 Day(s) Before": -35.480020000000025, "1 Day(s) Before": -10.25, "1 Day(s) After": 9.490010000000012, "3 Day(s) After": 12.420000000000016, "8 Day(s) After": 14.490010000000012, "13 Day(s) After": 5.040010000000024, "21 Day(s) After": 17.050010000000015, "34 Day(s) After": 25.770010000000013, "100 Day(s) After": null, "200 Day(s) After": null, "300 Day(s) After": null, "400 Day(s) After": null}, "2021-03-08": {"300 Day(s) Before": null, "100 Day(s) Before": null, "30 Day(s) Before": null, "10 Day(s) Before": -31.44999999999999, "3 Day(s) Before": -16.439999999999998, "1 Day(s) Before": 9.490010000000012, "1 Day(s) After": 5.570009999999996, "3 Day(s) After": 8.620000000000005, "8 Day(s) After": 1.3899999999999864, "13 Day(s) After": -10.25, "21 Day(s) After": 6.960010000000011, "34 Day(s) After": 13.0, "100 Day(s) After": null, "200 Day(s) After": null, "300 Day(s) After": null, "400 Day(s) After": null}, "2021-03-09": {"300 Day(s) Before": null, "100 Day(s) Before": null, "30 Day(s) Before": null, "10 Day(s) Before": -13.81998999999999, "3 Day(s) Before": 4.810020000000009, "1 Day(s) Before": 5.570009999999996, "1 Day(s) After": -2.6400199999999927, "3 Day(s) After": 4.289990000000017, "8 Day(s) After": -5.200009999999992, "13 Day(s) After": -11.380009999999999, "21 Day(s) After": 4.439979999999991, "34 Day(s) After": 13.539990000000017, "100 Day(s) After": null, "200 Day(s) After": null, "300 Day(s) After": null, "400 Day(s) After": null}, "2021-03-10": {"300 Day(s) Before": null, "100 Day(s) Before": null, "30 Day(s) Before": null, "10 Day(s) Before": -19.600009999999997, "3 Day(s) Before": 12.420000000000016, "1 Day(s) Before": -2.6400199999999927, "1 Day(s) After": 5.690010000000001, "3 Day(s) After": 10.200009999999992, "8 Day(s) After": 3.900010000000009, "13 Day(s) After": -8.609980000000007, "21 Day(s) After": 4.920019999999994, "34 Day(s) After": 14.270009999999985, "100 Day(s) After": null, "200 Day(s) After": null, "300 Day(s) After": null, "400 Day(s) After": null}, "2021-03-11": {"300 Day(s) Before": null, "100 Day(s) Before": null, "30 Day(s) Before": null, "10 Day(s) Before": -12.379999999999995, "3 Day(s) Before": 8.620000000000005, "1 Day(s) Before": 5.690010000000001, "1 Day(s) After": 1.240000000000009, "3 Day(s) After": -1.4099899999999934, "8 Day(s) After": -7.319999999999993, "13 Day(s) After": -13.120000000000005, "21 Day(s) After": -0.6200000000000045, "34 Day(s) After": 5.8799999999999955, "100 Day(s) After": null, "200 Day(s) After": null, "300 Day(s) After": null, "400 Day(s) After": null}, "2021-03-12": {"300 Day(s) Before": null, "100 Day(s) Before": null, "30 Day(s) Before": null, "10 Day(s) Before": -12.639999999999986, "3 Day(s) Before": 4.289990000000017, "1 Day(s) Before": 1.240000000000009, "1 Day(s) After": 3.269999999999982, "3 Day(s) After": -4.860000000000014, "8 Day(s) After": -14.310000000000002, "13 Day(s) After": -7.0, "21 Day(s) After": 1.399989999999974, "34 Day(s) After": 3.6399999999999864, "100 Day(s) After": null, "200 Day(s) After": null, "300 Day(s) After": null, "400 Day(s) After": null}, "2021-03-15": {"300 Day(s) Before": null, "100 Day(s) Before": null, "30 Day(s) Before": null, "10 Day(s) Before": -16.590000000000003, "3 Day(s) Before": 10.200009999999992, "1 Day(s) Before": 3.269999999999982, "1 Day(s) After": -5.919989999999984, "3 Day(s) After": -11.740000000000009, "8 Day(s) After": -23.379999999999995, "13 Day(s) After": -8.079999999999984, "21 Day(s) After": 1.460000000000008, "34 Day(s) After": -1.980009999999993, "100 Day(s) After": null, "200 Day(s) After": null, "300 Day(s) After": null, "400 Day(s) After": null}, "2021-03-16": {"300 Day(s) Before": null, "100 Day(s) Before": null, "30 Day(s) Before": null, "10 Day(s) Before": -18.78, "3 Day(s) Before": -1.4099899999999934, "1 Day(s) Before": -5.919989999999984, "1 Day(s) After": -2.210010000000011, "3 Day(s) After": -6.840010000000007, "8 Day(s) After": -13.020010000000013, "13 Day(s) After": -0.7100100000000111, "21 Day(s) After": 7.289989999999989, "34 Day(s) After": -2.9900100000000123, "100 Day(s) After": null, "200 Day(s) After": null, "300 Day(s) After": null, "400 Day(s) After": null}, "2021-03-17": {"300 Day(s) Before": null, "100 Day(s) Before": null, "30 Day(s) Before": null, "10 Day(s) Before": -11.439999999999998, "3 Day(s) Before": -4.860000000000014, "1 Day(s) Before": -2.210010000000011, "1 Day(s) After": -3.6100000000000136, "3 Day(s) After": 1.8300000000000125, "8 Day(s) After": -10.679990000000004, "13 Day(s) After": 2.5600000000000023, "21 Day(s) After": 8.560000000000002, "34 Day(s) After": -2.3400000000000034, "100 Day(s) After": null, "200 Day(s) After": null, "300 Day(s) After": null, "400 Day(s) After": null}, "2021-03-18": {"300 Day(s) Before": null, "100 Day(s) Before": null, "30 Day(s) Before": null, "10 Day(s) Before": 0.6300099999999986, "3 Day(s) Before": -11.740000000000009, "1 Day(s) Before": -3.6100000000000136, "1 Day(s) After": -1.0199999999999818, "3 Day(s) After": -0.08999999999997499, "8 Day(s) After": -5.889999999999986, "13 Day(s) After": 5.570010000000025, "21 Day(s) After": 6.310000000000002, "34 Day(s) After": -10.549999999999983, "100 Day(s) After": null, "200 Day(s) After": null, "300 Day(s) After": null, "400 Day(s) After": null}, "2021-03-19": {"300 Day(s) Before": null, "100 Day(s) Before": null, "30 Day(s) Before": null, "10 Day(s) Before": 9.860010000000017, "3 Day(s) Before": -6.840010000000007, "1 Day(s) Before": -1.0199999999999818, "1 Day(s) After": 6.460000000000008, "3 Day(s) After": -4.819999999999993, "8 Day(s) After": 2.490000000000009, "13 Day(s) After": 9.639989999999983, "21 Day(s) After": 9.389989999999983, "34 Day(s) After": -5.799990000000008, "100 Day(s) After": null, "200 Day(s) After": null, "300 Day(s) After": null, "400 Day(s) After": null}, "2021-03-22": {"300 Day(s) Before": null, "100 Day(s) Before": null, "30 Day(s) Before": null, "10 Day(s) Before": 6.8300000000000125, "3 Day(s) Before": 1.8300000000000125, "1 Day(s) Before": 6.460000000000008, "1 Day(s) After": -5.530000000000001, "3 Day(s) After": -17.080000000000013, "8 Day(s) After": -1.7800000000000011, "13 Day(s) After": 1.020009999999985, "21 Day(s) After": 3.329999999999984, "34 Day(s) After": -16.830000000000013, "100 Day(s) After": null, "200 Day(s) After": null, "300 Day(s) After": null, "400 Day(s) After": null}, "2021-03-23": {"300 Day(s) Before": null, "100 Day(s) Before": null, "30 Day(s) Before": null, "10 Day(s) Before": -4.270009999999985, "3 Day(s) Before": -0.08999999999997499, "1 Day(s) Before": -5.530000000000001, "1 Day(s) After": -5.75, "3 Day(s) After": -7.110000000000014, "8 Day(s) After": 5.199999999999989, "13 Day(s) After": 6.699999999999989, "21 Day(s) After": 11.300009999999986, "34 Day(s) After": -15.640000000000015, "100 Day(s) After": null, "200 Day(s) After": null, "300 Day(s) After": null, "400 Day(s) After": null}, "2021-03-24": {"300 Day(s) Before": null, "100 Day(s) Before": null, "30 Day(s) Before": null, "10 Day(s) Before": -7.379989999999992, "3 Day(s) Before": -4.819999999999993, "1 Day(s) Before": -5.75, "1 Day(s) After": -5.800000000000011, "3 Day(s) After": -1.229990000000015, "8 Day(s) After": 12.009999999999991, "13 Day(s) After": 15.709989999999976, "21 Day(s) After": 20.72999999999999, "34 Day(s) After": -9.780000000000015, "100 Day(s) After": null, "200 Day(s) After": null, "300 Day(s) After": null, "400 Day(s) After": null}, "2021-03-25": {"300 Day(s) Before": null, "100 Day(s) Before": null, "30 Day(s) Before": null, "10 Day(s) Before": -18.870000000000005, "3 Day(s) Before": -17.080000000000013, "1 Day(s) Before": -5.800000000000011, "1 Day(s) After": 4.439999999999998, "3 Day(s) After": 5.75, "8 Day(s) After": 17.21001000000001, "13 Day(s) After": 24.840000000000003, "21 Day(s) After": 23.25, "34 Day(s) After": -4.230000000000004, "100 Day(s) After": null, "200 Day(s) After": null, "300 Day(s) After": null, "400 Day(s) After": null}, "2021-03-26": {"300 Day(s) Before": null, "100 Day(s) Before": null, "30 Day(s) Before": null, "10 Day(s) Before": -15.670000000000016, "3 Day(s) Before": -7.110000000000014, "1 Day(s) Before": 4.439999999999998, "1 Day(s) After": 0.13000999999999863, "3 Day(s) After": 8.670000000000016, "8 Day(s) After": 15.81998999999999, "13 Day(s) After": 20.310000000000002, "21 Day(s) After": 24.920000000000016, "34 Day(s) After": -3.5999999999999943, "100 Day(s) After": null, "200 Day(s) After": null, "300 Day(s) After": null, "400 Day(s) After": null}, "2021-03-29": {"300 Day(s) Before": null, "100 Day(s) Before": null, "30 Day(s) Before": null, "10 Day(s) Before": -18.80999, "3 Day(s) Before": -1.229990000000015, "1 Day(s) Before": 0.13000999999999863, "1 Day(s) After": 1.1799900000000036, "3 Day(s) After": 10.729990000000015, "8 Day(s) After": 13.530000000000001, "13 Day(s) After": 19.239990000000006, "21 Day(s) After": 22.879989999999992, "34 Day(s) After": -1.3900199999999927, "100 Day(s) After": null, "200 Day(s) After": null, "300 Day(s) After": null, "400 Day(s) After": null}, "2021-03-30": {"300 Day(s) Before": null, "100 Day(s) Before": null, "30 Day(s) Before": -42.91999999999999, "10 Day(s) Before": -11.710010000000011, "3 Day(s) Before": 5.75, "1 Day(s) Before": 1.1799900000000036, "1 Day(s) After": 7.360000000000014, "3 Day(s) After": 11.0, "8 Day(s) After": 12.5, "13 Day(s) After": 12.199999999999989, "21 Day(s) After": 19.0, "34 Day(s) After": -11.909999999999997, "100 Day(s) After": null, "200 Day(s) After": null, "300 Day(s) After": null, "400 Day(s) After": null}, "2021-03-31": {"300 Day(s) Before": null, "100 Day(s) Before": null, "30 Day(s) Before": -34.639999999999986, "10 Day(s) Before": -2.1399999999999864, "3 Day(s) Before": 8.670000000000016, "1 Day(s) Before": 7.360000000000014, "1 Day(s) After": 2.1899999999999977, "3 Day(s) After": 4.699999999999989, "8 Day(s) After": 8.399989999999974, "13 Day(s) After": 6.899989999999974, "21 Day(s) After": 10.639999999999986, "34 Day(s) After": -16.830000000000013, "100 Day(s) After": null, "200 Day(s) After": null, "300 Day(s) After": null, "400 Day(s) After": null}, "2021-04-01": {"300 Day(s) Before": null, "100 Day(s) Before": null, "30 Day(s) Before": -28.579999999999984, "10 Day(s) Before": 3.660000000000025, "3 Day(s) Before": 10.729990000000015, "1 Day(s) Before": 2.1899999999999977, "1 Day(s) After": 1.4499999999999886, "3 Day(s) After": 1.9100099999999998, "8 Day(s) After": 9.539999999999992, "13 Day(s) After": 5.109999999999985, "21 Day(s) After": 6.099989999999991, "34 Day(s) After": -15.460000000000008, "100 Day(s) After": null, "200 Day(s) After": null, "300 Day(s) After": null, "400 Day(s) After": null}, "2021-04-05": {"300 Day(s) Before": null, "100 Day(s) Before": null, "30 Day(s) Before": -31.990010000000012, "10 Day(s) Before": 6.1299999999999955, "3 Day(s) Before": 11.0, "1 Day(s) Before": 1.4499999999999886, "1 Day(s) After": 1.0600000000000023, "3 Day(s) After": 3.5099899999999877, "8 Day(s) After": 8.0, "13 Day(s) After": 6.1000099999999975, "21 Day(s) After": -2.280000000000001, "34 Day(s) After": -17.519999999999996, "100 Day(s) After": null, "200 Day(s) After": null, "300 Day(s) After": null, "400 Day(s) After": null}, "2021-04-06": {"300 Day(s) Before": null, "100 Day(s) Before": null, "30 Day(s) Before": -23.889999999999986, "10 Day(s) Before": 0.7299999999999898, "3 Day(s) Before": 4.699999999999989, "1 Day(s) Before": 1.0600000000000023, "1 Day(s) After": -0.5999899999999911, "3 Day(s) After": 0.2900099999999952, "8 Day(s) After": 6.0, "13 Day(s) After": 8.719999999999999, "21 Day(s) After": -4.900000000000006, "34 Day(s) After": -17.200000000000003, "100 Day(s) After": null, "200 Day(s) After": null, "300 Day(s) After": null, "400 Day(s) After": null}, "2021-04-07": {"300 Day(s) Before": null, "100 Day(s) Before": null, "30 Day(s) Before": -12.429989999999975, "10 Day(s) Before": 5.66001, "3 Day(s) Before": 1.9100099999999998, "1 Day(s) Before": -0.5999899999999911, "1 Day(s) After": 3.0499799999999766, "3 Day(s) After": 1.0399899999999889, "8 Day(s) After": 0.7399899999999775, "13 Day(s) After": 6.039989999999989, "21 Day(s) After": -16.120010000000008, "34 Day(s) After": -13.840010000000007, "100 Day(s) After": null, "200 Day(s) After": null, "300 Day(s) After": null, "400 Day(s) After": null}, "2021-04-08": {"300 Day(s) Before": null, "100 Day(s) Before": null, "30 Day(s) Before": -12.520010000000013, "10 Day(s) Before": 14.459989999999976, "3 Day(s) Before": 3.5099899999999877, "1 Day(s) Before": 3.0499799999999766, "1 Day(s) After": -2.1599799999999902, "3 Day(s) After": 1.25, "8 Day(s) After": -0.25, "13 Day(s) After": 9.100010000000026, "21 Day(s) After": -15.439979999999991, "34 Day(s) After": -16.129989999999992, "100 Day(s) After": null, "200 Day(s) After": null, "300 Day(s) After": null, "400 Day(s) After": null}, "2021-04-09": {"300 Day(s) Before": null, "100 Day(s) Before": null, "30 Day(s) Before": -13.149990000000003, "10 Day(s) Before": 18.100009999999997, "3 Day(s) Before": 0.2900099999999952, "1 Day(s) Before": -2.1599799999999902, "1 Day(s) After": 0.1499900000000025, "3 Day(s) After": 6.739990000000006, "8 Day(s) After": 2.309989999999999, "13 Day(s) After": 9.349989999999991, "21 Day(s) After": -17.850009999999997, "34 Day(s) After": -10.280000000000001, "100 Day(s) After": null, "200 Day(s) After": null, "300 Day(s) After": null, "400 Day(s) After": null}, "2021-04-12": {"300 Day(s) Before": null, "100 Day(s) Before": null, "30 Day(s) Before": -14.5, "10 Day(s) Before": 13.810000000000002, "3 Day(s) Before": 1.0399899999999889, "1 Day(s) Before": 0.1499900000000025, "1 Day(s) After": 3.2599899999999877, "3 Day(s) After": 6.5, "8 Day(s) After": 4.6000099999999975, "13 Day(s) After": 6.5, "21 Day(s) After": -22.340000000000003, "34 Day(s) After": -6.02000000000001, "100 Day(s) After": null, "200 Day(s) After": null, "300 Day(s) After": null, "400 Day(s) After": null}, "2021-04-13": {"300 Day(s) Before": null, "100 Day(s) Before": null, "30 Day(s) Before": -18.46001000000001, "10 Day(s) Before": 16.93997999999999, "3 Day(s) Before": 1.25, "1 Day(s) Before": 3.2599899999999877, "1 Day(s) After": 3.3300100000000157, "3 Day(s) After": 2.3000100000000145, "8 Day(s) After": 5.020010000000013, "13 Day(s) After": 2.2400100000000123, "21 Day(s) After": -25.48998999999999, "34 Day(s) After": -12.229989999999987, "100 Day(s) After": null, "200 Day(s) After": null, "300 Day(s) After": null, "400 Day(s) After": null}, "2021-04-14": {"300 Day(s) Before": null, "100 Day(s) Before": null, "30 Day(s) Before": -11.400010000000009, "10 Day(s) Before": 19.090000000000003, "3 Day(s) Before": 6.739990000000006, "1 Day(s) Before": 3.3300100000000157, "1 Day(s) After": -0.09000000000000341, "3 Day(s) After": -6.890000000000015, "8 Day(s) After": -1.5900000000000034, "13 Day(s) After": -3.440010000000001, "21 Day(s) After": -29.070000000000007, "34 Day(s) After": -14.755300000000005, "100 Day(s) After": null, "200 Day(s) After": null, "300 Day(s) After": null, "400 Day(s) After": null}, "2021-04-15": {"300 Day(s) Before": null, "100 Day(s) Before": null, "30 Day(s) Before": -1.9399999999999977, "10 Day(s) Before": 11.639999999999986, "3 Day(s) Before": 6.5, "1 Day(s) Before": -0.09000000000000341, "1 Day(s) After": -0.9399999999999977, "3 Day(s) After": -4.740010000000012, "8 Day(s) After": 4.610000000000014, "13 Day(s) After": -10.280000000000001, "21 Day(s) After": -23.909999999999997, "34 Day(s) After": -14.550000000000011, "100 Day(s) After": null, "200 Day(s) After": null, "300 Day(s) After": null, "400 Day(s) After": null}, "2021-04-16": {"300 Day(s) Before": null, "100 Day(s) Before": null, "30 Day(s) Before": 12.800010000000015, "10 Day(s) Before": 8.509999999999991, "3 Day(s) Before": 2.3000100000000145, "1 Day(s) Before": -0.9399999999999977, "1 Day(s) After": -5.860000000000014, "3 Day(s) After": -3.4000000000000057, "8 Day(s) After": 3.6399999999999864, "13 Day(s) After": -10.900000000000006, "21 Day(s) After": -20.63001, "34 Day(s) After": -12.719999999999999, "100 Day(s) After": null, "200 Day(s) After": null, "300 Day(s) After": null, "400 Day(s) After": null}, "2021-04-19": {"300 Day(s) Before": null, "100 Day(s) Before": null, "30 Day(s) Before": 17.19001, "10 Day(s) Before": 1.1999999999999886, "3 Day(s) Before": -6.890000000000015, "1 Day(s) Before": -5.860000000000014, "1 Day(s) After": 2.059989999999999, "3 Day(s) After": 4.900010000000009, "8 Day(s) After": 6.800000000000011, "13 Day(s) After": -16.859999999999985, "21 Day(s) After": -24.109999999999985, "34 Day(s) After": -5.449999999999989, "100 Day(s) After": null, "200 Day(s) After": null, "300 Day(s) After": null, "400 Day(s) After": null}, "2021-04-20": {"300 Day(s) Before": null, "100 Day(s) Before": null, "30 Day(s) Before": 9.759989999999988, "10 Day(s) Before": 2.1999899999999855, "3 Day(s) Before": -4.740010000000012, "1 Day(s) Before": 2.059989999999999, "1 Day(s) After": 0.40001000000000886, "3 Day(s) After": 6.520010000000013, "8 Day(s) After": 3.7400100000000123, "13 Day(s) After": -15.189979999999991, "21 Day(s) After": -23.729989999999987, "34 Day(s) After": -1.31998999999999, "100 Day(s) After": null, "200 Day(s) After": null, "300 Day(s) After": null, "400 Day(s) After": null}, "2021-04-21": {"300 Day(s) Before": null, "100 Day(s) Before": null, "30 Day(s) Before": 4.58999, "10 Day(s) Before": 3.1999899999999855, "3 Day(s) Before": -3.4000000000000057, "1 Day(s) Before": 0.40001000000000886, "1 Day(s) After": 2.440010000000001, "3 Day(s) After": 2.8400000000000034, "8 Day(s) After": 0.9899900000000059, "13 Day(s) After": -20.159999999999997, "21 Day(s) After": -20.569999999999993, "34 Day(s) After": 0.16000999999999976, "100 Day(s) After": null, "200 Day(s) After": null, "300 Day(s) After": null, "400 Day(s) After": null}, "2021-04-22": {"300 Day(s) Before": null, "100 Day(s) Before": null, "30 Day(s) Before": 9.670019999999994, "10 Day(s) Before": 2.5900200000000098, "3 Day(s) Before": 4.900010000000009, "1 Day(s) Before": 2.440010000000001, "1 Day(s) After": 3.6799900000000036, "3 Day(s) After": 6.509990000000016, "8 Day(s) After": -8.380009999999999, "13 Day(s) After": -26.94001, "21 Day(s) After": -23.620009999999994, "34 Day(s) After": -2.980009999999993, "100 Day(s) After": null, "200 Day(s) After": null, "300 Day(s) After": null, "400 Day(s) After": null}, "2021-04-23": {"300 Day(s) Before": null, "100 Day(s) Before": null, "30 Day(s) Before": 7.659999999999997, "10 Day(s) Before": 8.429990000000004, "3 Day(s) Before": 6.520010000000013, "1 Day(s) Before": 3.6799900000000036, "1 Day(s) After": -3.280000000000001, "3 Day(s) After": 0.9199999999999875, "8 Day(s) After": -13.620000000000005, "13 Day(s) After": -30.510000000000005, "21 Day(s) After": -25.92, "34 Day(s) After": -2.2700100000000134, "100 Day(s) After": null, "200 Day(s) After": null, "300 Day(s) After": null, "400 Day(s) After": null}, "2021-04-26": {"300 Day(s) Before": null, "100 Day(s) Before": null, "30 Day(s) Before": 3.1399999999999864, "10 Day(s) Before": 5.0, "3 Day(s) Before": 2.8400000000000034, "1 Day(s) Before": -3.280000000000001, "1 Day(s) After": 6.110000000000014, "3 Day(s) After": 1.5, "8 Day(s) After": -22.159999999999997, "13 Day(s) After": -27.480000000000004, "21 Day(s) After": -19.879999999999995, "34 Day(s) After": null, "100 Day(s) After": null, "200 Day(s) After": null, "300 Day(s) After": null, "400 Day(s) After": null}, "2021-04-27": {"300 Day(s) Before": null, "100 Day(s) Before": null, "30 Day(s) Before": 5.980000000000018, "10 Day(s) Before": 7.850010000000026, "3 Day(s) Before": 6.509990000000016, "1 Day(s) Before": 6.110000000000014, "1 Day(s) After": -1.910000000000025, "3 Day(s) After": -5.610000000000014, "8 Day(s) After": -24.539990000000017, "13 Day(s) After": -28.52000000000001, "21 Day(s) After": -25.230000000000018, "34 Day(s) After": null, "100 Day(s) After": null, "200 Day(s) After": null, "300 Day(s) After": null, "400 Day(s) After": null}, "2021-04-28": {"300 Day(s) Before": null, "100 Day(s) Before": null, "30 Day(s) Before": 9.989989999999977, "10 Day(s) Before": 2.609999999999985, "3 Day(s) Before": 0.9199999999999875, "1 Day(s) Before": -1.910000000000025, "1 Day(s) After": -2.6999999999999886, "3 Day(s) After": -6.050009999999986, "8 Day(s) After": -27.19999999999999, "13 Day(s) After": -24.270009999999985, "21 Day(s) After": -19.629989999999992, "34 Day(s) After": null, "100 Day(s) After": null, "200 Day(s) After": null, "300 Day(s) After": null, "400 Day(s) After": null}, "2021-04-29": {"300 Day(s) Before": null, "100 Day(s) Before": null, "30 Day(s) Before": 9.5, "10 Day(s) Before": 0.0, "3 Day(s) Before": 1.5, "1 Day(s) Before": -2.6999999999999886, "1 Day(s) After": -1.0, "3 Day(s) After": -10.280000000000001, "8 Day(s) After": -28.840000000000003, "13 Day(s) After": -30.909999999999997, "21 Day(s) After": -12.52000000000001, "34 Day(s) After": null, "100 Day(s) After": null, "200 Day(s) After": null, "300 Day(s) After": null, "400 Day(s) After": null}, "2021-04-30": {"300 Day(s) Before": null, "100 Day(s) Before": null, "30 Day(s) Before": 12.110000000000014, "10 Day(s) Before": -0.060000000000002274, "3 Day(s) Before": -5.610000000000014, "1 Day(s) Before": -1.0, "1 Day(s) After": -2.3500099999999975, "3 Day(s) After": -10.840000000000003, "8 Day(s) After": -27.730000000000004, "13 Day(s) After": -27.47, "21 Day(s) After": -14.469999999999999, "34 Day(s) After": null, "100 Day(s) After": null, "200 Day(s) After": null, "300 Day(s) After": null, "400 Day(s) After": null}, "2021-05-03": {"300 Day(s) Before": null, "100 Day(s) Before": null, "30 Day(s) Before": 10.779989999999998, "10 Day(s) Before": 3.449990000000014, "3 Day(s) Before": -6.050009999999986, "1 Day(s) Before": -2.3500099999999975, "1 Day(s) After": -6.929990000000004, "3 Day(s) After": -20.30999, "8 Day(s) After": -25.629990000000006, "13 Day(s) After": -21.55999, "21 Day(s) After": -11.315290000000005, "34 Day(s) After": null, "100 Day(s) After": null, "200 Day(s) After": null, "300 Day(s) After": null, "400 Day(s) After": null}, "2021-05-04": {"300 Day(s) Before": null, "100 Day(s) Before": null, "30 Day(s) Before": -2.6100000000000136, "10 Day(s) Before": -5.539989999999989, "3 Day(s) Before": -10.280000000000001, "1 Day(s) Before": -6.929990000000004, "1 Day(s) After": -1.5600000000000023, "3 Day(s) After": -9.649990000000003, "8 Day(s) After": -13.629999999999995, "13 Day(s) After": -15.239999999999995, "21 Day(s) After": -4.27000000000001, "34 Day(s) After": null, "100 Day(s) After": null, "200 Day(s) After": null, "300 Day(s) After": null, "400 Day(s) After": null}, "2021-05-05": {"300 Day(s) Before": null, "100 Day(s) Before": null, "30 Day(s) Before": 1.3599999999999852, "10 Day(s) Before": -7.5, "3 Day(s) Before": -10.840000000000003, "1 Day(s) Before": -1.5600000000000023, "1 Day(s) After": -11.819999999999993, "3 Day(s) After": -12.659999999999997, "8 Day(s) After": -9.730009999999993, "13 Day(s) After": -12.299999999999997, "21 Day(s) After": -1.8199999999999932, "34 Day(s) After": null, "100 Day(s) After": null, "200 Day(s) After": null, "300 Day(s) After": null, "400 Day(s) After": null}, "2021-05-06": {"300 Day(s) Before": null, "100 Day(s) Before": null, "30 Day(s) Before": -4.710000000000008, "10 Day(s) Before": -21.760009999999994, "3 Day(s) Before": -20.30999, "1 Day(s) Before": -11.819999999999993, "1 Day(s) After": 3.730009999999993, "3 Day(s) After": -5.180000000000007, "8 Day(s) After": -7.25, "13 Day(s) After": 2.280000000000001, "21 Day(s) After": 11.409999999999997, "34 Day(s) After": null, "100 Day(s) After": null, "200 Day(s) After": null, "300 Day(s) After": null, "400 Day(s) After": null}, "2021-05-07": {"300 Day(s) Before": null, "100 Day(s) Before": null, "30 Day(s) Before": 4.820009999999996, "10 Day(s) Before": -21.709990000000005, "3 Day(s) Before": -9.649990000000003, "1 Day(s) Before": 3.730009999999993, "1 Day(s) After": -4.570009999999996, "3 Day(s) After": -8.80001, "8 Day(s) After": -8.540009999999995, "13 Day(s) After": -0.6900100000000009, "21 Day(s) After": 13.869990000000001, "34 Day(s) After": null, "100 Day(s) After": null, "200 Day(s) After": null, "300 Day(s) After": null, "400 Day(s) After": null}, "2021-05-10": {"300 Day(s) Before": null, "100 Day(s) Before": null, "30 Day(s) Before": -4.189999999999998, "10 Day(s) Before": -23.0, "3 Day(s) Before": -12.659999999999997, "1 Day(s) Before": -4.570009999999996, "1 Day(s) After": -4.340000000000003, "3 Day(s) After": -4.480000000000004, "8 Day(s) After": -0.4099999999999966, "13 Day(s) After": 7.570009999999996, "21 Day(s) After": 20.320009999999996, "34 Day(s) After": null, "100 Day(s) After": null, "200 Day(s) After": null, "300 Day(s) After": null, "400 Day(s) After": null}, "2021-05-11": {"300 Day(s) Before": null, "100 Day(s) Before": null, "30 Day(s) Before": -8.66001, "10 Day(s) Before": -33.45000000000002, "3 Day(s) Before": -5.180000000000007, "1 Day(s) Before": -4.340000000000003, "1 Day(s) After": 0.10999999999999943, "3 Day(s) After": 4.930000000000007, "8 Day(s) After": 3.3200000000000074, "13 Day(s) After": 16.319999999999993, "21 Day(s) After": 23.960000000000008, "34 Day(s) After": null, "100 Day(s) After": null, "200 Day(s) After": null, "300 Day(s) After": null, "400 Day(s) After": null}, "2021-05-12": {"300 Day(s) Before": null, "100 Day(s) Before": null, "30 Day(s) Before": -9.730000000000004, "10 Day(s) Before": -31.429999999999993, "3 Day(s) Before": -8.80001, "1 Day(s) Before": 0.10999999999999943, "1 Day(s) After": -0.25, "3 Day(s) After": 7.159990000000008, "8 Day(s) After": 4.590000000000003, "13 Day(s) After": 13.260000000000005, "21 Day(s) After": 28.23998999999999, "34 Day(s) After": null, "100 Day(s) After": null, "200 Day(s) After": null, "300 Day(s) After": null, "400 Day(s) After": null}, "2021-05-13": {"300 Day(s) Before": null, "100 Day(s) Before": null, "30 Day(s) Before": -17.340000000000018, "10 Day(s) Before": -28.980000000000004, "3 Day(s) Before": -4.480000000000004, "1 Day(s) Before": -0.25, "1 Day(s) After": 5.070000000000007, "3 Day(s) After": -1.9299999999999926, "8 Day(s) After": 7.6000000000000085, "13 Day(s) After": 14.314700000000002, "21 Day(s) After": null, "34 Day(s) After": null, "100 Day(s) After": null, "200 Day(s) After": null, "300 Day(s) After": null, "400 Day(s) After": null}, "2021-05-14": {"300 Day(s) Before": null, "100 Day(s) Before": null, "30 Day(s) Before": -14.460000000000008, "10 Day(s) Before": -22.909999999999997, "3 Day(s) Before": 4.930000000000007, "1 Day(s) Before": 5.070000000000007, "1 Day(s) After": 2.3399900000000002, "3 Day(s) After": -4.560000000000002, "8 Day(s) After": 3.289999999999992, "13 Day(s) After": 9.359999999999985, "21 Day(s) After": null, "34 Day(s) After": null, "100 Day(s) After": null, "200 Day(s) After": null, "300 Day(s) After": null, "400 Day(s) After": null}, "2021-05-17": {"300 Day(s) Before": null, "100 Day(s) Before": null, "30 Day(s) Before": -13.570009999999996, "10 Day(s) Before": -18.22, "3 Day(s) Before": 7.159990000000008, "1 Day(s) Before": 2.3399900000000002, "1 Day(s) After": -9.33999, "3 Day(s) After": -3.3399900000000002, "8 Day(s) After": 4.640019999999993, "13 Day(s) After": 7.91001, "21 Day(s) After": null, "34 Day(s) After": null, "100 Day(s) After": null, "200 Day(s) After": null, "300 Day(s) After": null, "400 Day(s) After": null}, "2021-05-18": {"300 Day(s) Before": null, "100 Day(s) Before": null, "30 Day(s) Before": -23.97, "10 Day(s) Before": -20.629999999999995, "3 Day(s) Before": -1.9299999999999926, "1 Day(s) Before": -9.33999, "1 Day(s) After": 2.4399999999999977, "3 Day(s) After": 5.390000000000001, "8 Day(s) After": 18.389999999999986, "13 Day(s) After": 18.659999999999997, "21 Day(s) After": null, "34 Day(s) After": null, "100 Day(s) After": null, "200 Day(s) After": null, "300 Day(s) After": null, "400 Day(s) After": null}, "2021-05-19": {"300 Day(s) Before": null, "100 Day(s) Before": null, "30 Day(s) Before": -20.93001000000001, "10 Day(s) Before": -16.629999999999995, "3 Day(s) Before": -4.560000000000002, "1 Day(s) Before": 2.4399999999999977, "1 Day(s) After": 3.5600000000000023, "3 Day(s) After": 4.329999999999998, "8 Day(s) After": 13.0, "13 Day(s) After": 22.409999999999997, "21 Day(s) After": null, "34 Day(s) After": null, "100 Day(s) After": null, "200 Day(s) After": null, "300 Day(s) After": null, "400 Day(s) After": null}, "2021-05-20": {"300 Day(s) Before": null, "100 Day(s) Before": null, "30 Day(s) Before": -20.419989999999984, "10 Day(s) Before": -1.25, "3 Day(s) Before": -3.3399900000000002, "1 Day(s) Before": 3.5600000000000023, "1 Day(s) After": -0.6099999999999994, "3 Day(s) After": 3.530000000000001, "8 Day(s) After": 10.244699999999995, "13 Day(s) After": 20.730009999999993, "21 Day(s) After": null, "34 Day(s) After": null, "100 Day(s) After": null, "200 Day(s) After": null, "300 Day(s) After": null, "400 Day(s) After": null}, "2021-05-21": {"300 Day(s) Before": null, "100 Day(s) Before": null, "30 Day(s) Before": -18.870009999999994, "10 Day(s) Before": -5.590009999999992, "3 Day(s) Before": 5.390000000000001, "1 Day(s) Before": -0.6099999999999994, "1 Day(s) After": 1.3799999999999955, "3 Day(s) After": 4.8999999999999915, "8 Day(s) After": 10.969999999999985, "13 Day(s) After": 20.64, "21 Day(s) After": null, "34 Day(s) After": null, "100 Day(s) After": null, "200 Day(s) After": null, "300 Day(s) After": null, "400 Day(s) After": null}, "2021-05-24": {"300 Day(s) Before": null, "100 Day(s) Before": null, "30 Day(s) Before": -17.64, "10 Day(s) Before": 0.35999999999999943, "3 Day(s) Before": 4.329999999999998, "1 Day(s) Before": 1.3799999999999955, "1 Day(s) After": 2.760000000000005, "3 Day(s) After": 7.210009999999997, "8 Day(s) After": 10.480000000000004, "13 Day(s) After": 23.64998999999999, "21 Day(s) After": null, "34 Day(s) After": null, "100 Day(s) After": null, "200 Day(s) After": null, "300 Day(s) After": null, "400 Day(s) After": null}, "2021-05-25": {"300 Day(s) Before": null, "100 Day(s) Before": null, "30 Day(s) Before": -18.139989999999983, "10 Day(s) Before": 7.460000000000008, "3 Day(s) Before": 3.530000000000001, "1 Day(s) Before": 2.760000000000005, "1 Day(s) After": 0.7599999999999909, "3 Day(s) After": 8.859999999999985, "8 Day(s) After": 9.129999999999995, "13 Day(s) After": null, "21 Day(s) After": null, "34 Day(s) After": null, "100 Day(s) After": null, "200 Day(s) After": null, "300 Day(s) After": null, "400 Day(s) After": null}, "2021-05-26": {"300 Day(s) Before": null, "100 Day(s) Before": null, "30 Day(s) Before": -20.710000000000008, "10 Day(s) Before": 8.11, "3 Day(s) Before": 4.8999999999999915, "1 Day(s) Before": 0.7599999999999909, "1 Day(s) After": 3.690010000000001, "3 Day(s) After": 5.150000000000006, "8 Day(s) After": 14.560000000000002, "13 Day(s) After": null, "21 Day(s) After": null, "34 Day(s) After": null, "100 Day(s) After": null, "200 Day(s) After": null, "300 Day(s) After": null, "400 Day(s) After": null}, "2021-05-27": {"300 Day(s) Before": null, "100 Day(s) Before": null, "30 Day(s) Before": -16.929990000000004, "10 Day(s) Before": 12.05001, "3 Day(s) Before": 7.210009999999997, "1 Day(s) Before": 3.690010000000001, "1 Day(s) After": 4.409989999999993, "3 Day(s) After": 2.2646900000000016, "8 Day(s) After": 12.75, "13 Day(s) After": null, "21 Day(s) After": null, "34 Day(s) After": null, "100 Day(s) After": null, "200 Day(s) After": null, "300 Day(s) After": null, "400 Day(s) After": null}, "2021-05-28": {"300 Day(s) Before": null, "100 Day(s) Before": null, "30 Day(s) Before": -11.580000000000013, "10 Day(s) Before": 11.389999999999986, "3 Day(s) Before": 8.859999999999985, "1 Day(s) Before": 4.409989999999993, "1 Day(s) After": -2.9499999999999886, "3 Day(s) After": -2.030000000000001, "8 Day(s) After": 7.640000000000015, "13 Day(s) After": null, "21 Day(s) After": null, "34 Day(s) After": null, "100 Day(s) After": null, "200 Day(s) After": null, "300 Day(s) After": null, "400 Day(s) After": null}, "2021-06-01": {"300 Day(s) Before": null, "100 Day(s) Before": null, "30 Day(s) Before": -8.669999999999987, "10 Day(s) Before": 6.1000099999999975, "3 Day(s) Before": 5.150000000000006, "1 Day(s) Before": -2.9499999999999886, "1 Day(s) After": 0.8046999999999969, "3 Day(s) After": 1.8100000000000023, "8 Day(s) After": 14.979989999999987, "13 Day(s) After": null, "21 Day(s) After": null, "34 Day(s) After": null, "100 Day(s) After": null, "200 Day(s) After": null, "300 Day(s) After": null, "400 Day(s) After": null}, "2021-06-02": {"300 Day(s) Before": null, "100 Day(s) Before": null, "30 Day(s) Before": -9.92528999999999, "10 Day(s) Before": 16.244699999999995, "3 Day(s) Before": 2.2646900000000016, "1 Day(s) Before": 0.8046999999999969, "1 Day(s) After": 0.11529999999999063, "3 Day(s) After": 2.415300000000002, "8 Day(s) After": null, "13 Day(s) After": null, "21 Day(s) After": null, "34 Day(s) After": null, "100 Day(s) After": null, "200 Day(s) After": null, "300 Day(s) After": null, "400 Day(s) After": null}, "2021-06-03": {"300 Day(s) Before": null, "100 Day(s) Before": null, "30 Day(s) Before": -10.210000000000008, "10 Day(s) Before": 13.919999999999987, "3 Day(s) Before": -2.030000000000001, "1 Day(s) Before": 0.11529999999999063, "1 Day(s) After": 0.8900000000000148, "3 Day(s) After": 8.490000000000009, "8 Day(s) After": null, "13 Day(s) After": null, "21 Day(s) After": null, "34 Day(s) After": null, "100 Day(s) After": null, "200 Day(s) After": null, "300 Day(s) After": null, "400 Day(s) After": null}, "2021-06-04": {"300 Day(s) Before": null, "100 Day(s) Before": null, "30 Day(s) Before": -11.760009999999994, "10 Day(s) Before": 11.25, "3 Day(s) Before": 1.8100000000000023, "1 Day(s) Before": 0.8900000000000148, "1 Day(s) After": 1.4099999999999966, "3 Day(s) After": 9.480009999999993, "8 Day(s) After": null, "13 Day(s) After": null, "21 Day(s) After": null, "34 Day(s) After": null, "100 Day(s) After": null, "200 Day(s) After": null, "300 Day(s) After": null, "400 Day(s) After": null}, "2021-06-07": {"300 Day(s) Before": null, "100 Day(s) Before": null, "30 Day(s) Before": -14.030000000000001, "10 Day(s) Before": 13.269999999999996, "3 Day(s) Before": 2.415300000000002, "1 Day(s) Before": 1.4099999999999966, "1 Day(s) After": 6.189999999999998, "3 Day(s) After": 7.3700000000000045, "8 Day(s) After": null, "13 Day(s) After": null, "21 Day(s) After": null, "34 Day(s) After": null, "100 Day(s) After": null, "200 Day(s) After": null, "300 Day(s) After": null, "400 Day(s) After": null}, "2021-06-08": {"300 Day(s) Before": null, "100 Day(s) Before": null, "30 Day(s) Before": -4.560000000000002, "10 Day(s) Before": 18.08, "3 Day(s) Before": 8.490000000000009, "1 Day(s) Before": 6.189999999999998, "1 Day(s) After": 1.8800099999999986, "3 Day(s) After": 5.56998999999999, "8 Day(s) After": null, "13 Day(s) After": null, "21 Day(s) After": null, "34 Day(s) After": null, "100 Day(s) After": null, "200 Day(s) After": null, "300 Day(s) After": null, "400 Day(s) After": null}, "2021-06-09": {"300 Day(s) Before": null, "100 Day(s) Before": null, "30 Day(s) Before": -8.789990000000017, "10 Day(s) Before": 17.200009999999992, "3 Day(s) Before": 9.480009999999993, "1 Day(s) Before": 1.8800099999999986, "1 Day(s) After": -0.7000099999999918, "3 Day(s) After": null, "8 Day(s) After": null, "13 Day(s) After": null, "21 Day(s) After": null, "34 Day(s) After": null, "100 Day(s) After": null, "200 Day(s) After": null, "300 Day(s) After": null, "400 Day(s) After": null}, "2021-06-10": {"300 Day(s) Before": null, "100 Day(s) Before": null, "30 Day(s) Before": -7.579999999999984, "10 Day(s) Before": 15.740000000000009, "3 Day(s) Before": 7.3700000000000045, "1 Day(s) Before": -0.7000099999999918, "1 Day(s) After": 4.389989999999983, "3 Day(s) After": null, "8 Day(s) After": null, "13 Day(s) After": null, "21 Day(s) After": null, "34 Day(s) After": null, "100 Day(s) After": null, "200 Day(s) After": null, "300 Day(s) After": null, "400 Day(s) After": null}, "2021-06-11": {"300 Day(s) Before": null, "100 Day(s) Before": null, "30 Day(s) Before": -0.49001000000001227, "10 Day(s) Before": 16.43997999999999, "3 Day(s) Before": 5.56998999999999, "1 Day(s) Before": 4.389989999999983, "1 Day(s) After": null, "3 Day(s) After": null, "8 Day(s) After": null, "13 Day(s) After": null, "21 Day(s) After": null, "34 Day(s) After": null, "100 Day(s) After": null, "200 Day(s) After": null, "300 Day(s) After": null, "400 Day(s) After": null}}}